{
  "section_order": [
    "photo",
    "bio",
    "skills",
    "projects",
    "contact",
    "social"
  ],
  "color_scheme": "solar_noon",
  "bio": {
    "name": "Nico Daunt",
    "title": "Full-Stack Developer / / Genius Mode",
    "summary": "Passionate developer with 34 years of experience building web applications. I love creating tools that make people's lives easier and learning new technologies along the way."
  },
  "photo": {
    "url": "https://encrypted-tbn0.gstatic.com/images?q=tbn:ANd9GcQYEwNxuq5KhYo43uZkRZS-Q3CQXI6IH0hkWA&s"
  },
  "skills": [
    "JavaScript",
    "Python",
    "React",
    "Node.js",
    "SQL",
    "Git",
    "REST APIs",
    "CSS/Sass"
  ],
  "projects": [
    {
      "title": "Pokemon App",
      "description": "Combinatorics thing for pokemon",
      "link": "https://github.com/vrnico/day4-pokemon"
    },
    {
      "title": "Weather Dashboard",
      "description": "A responsive weather application that displays current conditions and 5-day forecasts using the OpenWeather API.",
      "link": "https://github.com"
    }
  ],
  "contact": {
    "email": "hello@nicodaunt.com",
    "phone": "",
    "location": "Los Angeles, CA"
  },
  "social": {
    "linkedin": "https://linkedin.com/in/example",
    "github": "https://github.com/example",
    "instagram": ""
  }
}